{"namedChunkGroups":{"polyfill":{"name":"polyfill","assets":[{"name":"webpack-runtime-3674f4c080902bcf0671.js","size":4904},{"name":"polyfill-b850f368c67584990052.js","size":82639}],"filteredAssets":0,"assetsSize":87543,"filteredAuxiliaryAssets":2,"auxiliaryAssetsSize":221083},"app":{"name":"app","assets":[{"name":"webpack-runtime-3674f4c080902bcf0671.js","size":4904},{"name":"framework-0b2e71d0ac8421f61892.js","size":128967},{"name":"app-710fa8fb7bebe9c87f28.js","size":66070}],"filteredAssets":0,"assetsSize":199941,"filteredAuxiliaryAssets":3,"auxiliaryAssetsSize":648624},"component---src-pages-404-js":{"name":"component---src-pages-404-js","assets":[{"name":"component---src-pages-404-js-909496862a98073996d4.js","size":816}],"filteredAssets":0,"assetsSize":816,"filteredAuxiliaryAssets":1,"auxiliaryAssetsSize":1889},"component---src-pages-index-js":{"name":"component---src-pages-index-js","assets":[{"name":"styles.4fce8be1018e5522ce41.css","size":11919},{"name":"a9a7754c-b940562d0915a6f79250.js","size":2692},{"name":"component---src-pages-index-js-8ff0d8dfb6292399fc19.js","size":35520}],"filteredAssets":0,"assetsSize":50131,"filteredAuxiliaryAssets":7,"auxiliaryAssetsSize":877948}},"assetsByChunkName":{"polyfill":["webpack-runtime-3674f4c080902bcf0671.js","polyfill-b850f368c67584990052.js"],"app":["webpack-runtime-3674f4c080902bcf0671.js","framework-0b2e71d0ac8421f61892.js","app-710fa8fb7bebe9c87f28.js"],"component---src-pages-404-js":["component---src-pages-404-js-909496862a98073996d4.js"],"component---src-pages-index-js":["styles.4fce8be1018e5522ce41.css","a9a7754c-b940562d0915a6f79250.js","component---src-pages-index-js-8ff0d8dfb6292399fc19.js"]},"childAssetsByChunkName":{}}